mcp_server_docker/__init__.py
mcp_server_docker/input_schemas.py
mcp_server_docker/output_schemas.py
mcp_server_docker/server.py
mcp_server_docker/settings.py
mcp_server_docker-0.2.1.dist-info/METADATA
mcp_server_docker-0.2.1.dist-info/WHEEL
mcp_server_docker-0.2.1.dist-info/entry_points.txt
mcp_server_docker-0.2.1.dist-info/licenses/LICENSE
mcp_server_docker-0.2.1.dist-info/RECORD
