Metadata-Version: 2.4
Name: mcp-server-docker
Version: 0.2.1
Summary: A Docker MCP Server
Project-URL: Repository, https://github.com/ckreiling/mcp-server-docker
Project-URL: Issues, https://github.com/ckreiling/mcp-server-docker/issues
Author-email: Christian Kreiling <kreiling@hey.com>
License:                     GNU GENERAL PUBLIC LICENSE
License-File: LICENSE
Keywords: docker,mcp,server
Classifier: Development Status :: 4 - Beta
Classifier: Programming Language :: Python :: 3.12
Requires-Python: >=3.12
Requires-Dist: docker>=7.1.0
Requires-Dist: mcp<2.0,>=1.1.0
Requires-Dist: paramiko<4.0,>=3.5.1
Requires-Dist: pydantic-settings>=2.6.1
Requires-Dist: pydantic>=2.10.3
